talisman_ie_rubricator-0.0.4.data/data/VERSION
tie_rubricator/__init__.py
tie_rubricator/datamodel/__init__.py
tie_rubricator/datamodel/description.py
tie_rubricator/datamodel/domain.py
tie_rubricator/datamodel/model.py
tie_rubricator/datamodel/rubric.py
tie_rubricator/datamodel/rubricator.py
tie_rubricator/datamodel/rubricator_serializable.py
tie_rubricator/processor/__init__.py
tie_rubricator/processor/abstract.py
tie_rubricator/provider/__init__.py
tie_rubricator/provider/abstract.py
tie_rubricator/provider/api/__init__.py
tie_rubricator/provider/api/config.py
tie_rubricator/provider/api/provider.py
tie_rubricator/provider/api/_impl/_0_17_0.py
tie_rubricator/provider/api/_impl/__init__.py
tie_rubricator/provider/api/_impl/graphql/0.17.0/public.graphql
tie_rubricator/provider/local/__init__.py
tie_rubricator/provider/local/config.py
tie_rubricator/provider/local/provider.py
talisman_ie_rubricator-0.0.4.dist-info/METADATA
talisman_ie_rubricator-0.0.4.dist-info/WHEEL
talisman_ie_rubricator-0.0.4.dist-info/top_level.txt
talisman_ie_rubricator-0.0.4.dist-info/RECORD
