Metadata-Version: 2.4
Name: talisman-ie-rubricator
Version: 0.0.4
Summary: Talisman-IE toolkit for automatic rubrication
Author: ISPRAS Talisman NLP team
Author-email: modis@ispras.ru
Maintainer: Vladimir Mayorov
Maintainer-email: vmayorov@ispras.ru
License: Apache Software License
Classifier: Development Status :: 3 - Alpha
Classifier: Programming Language :: Python :: 3
Classifier: Programming Language :: Python :: 3.10
Classifier: Programming Language :: Python :: 3.11
Classifier: Intended Audience :: Developers
Classifier: Operating System :: OS Independent
Classifier: License :: OSI Approved :: Apache Software License
Requires-Python: >=3.10
Requires-Dist: talisman-interfaces<0.12,>=0.11.8
Requires-Dist: talisman-api~=1.4
Requires-Dist: talisman-domain~=0.4.8
Requires-Dist: talisman-dm<2,>=1.3.8
Dynamic: author
Dynamic: author-email
Dynamic: classifier
Dynamic: description
Dynamic: description-content-type
Dynamic: license
Dynamic: maintainer
Dynamic: maintainer-email
Dynamic: requires-dist
Dynamic: requires-python
Dynamic: summary
